corylus/__init__.py
corylus/log/__init__.py
corylus/log/config.py
corylus/log/dates.py
corylus/log/db.py
corylus/log/handler.py
corylus/log/query.py
corylus/log/queueing.py
corylus/time/__init__.py
corylus/time/between.py
corylus/time/cli.py
corylus/time/date.py
corylus/time/epoch2jd.py
corylus/time/format.py
corylus/time/from_datetime.py
corylus/time/jd2epoch.py
corylus/time/julian_date.py
corylus/time/julian_day.py
corylus/time/local2utc.py
corylus/time/now.py
corylus/time/to_datetime.py
corylus/time/until.py
corylus/time/until_next_hour.py
corylus/time/until_next_minutes.py
corylus/util/__init__.py
corylus/util/array.py
corylus/util/csv.py
corylus/util/first.py
corylus/util/home2tilde.py
corylus/util/isiterator.py
corylus/util/json_encoder.py
corylus/util/last.py
corylus/util/load.py
corylus/util/merge.py
corylus/util/prune.py
corylus/util/re_uuid.py
corylus/util/substitute.py
corylus/util/to_json.py
corylus/util/to_yaml.py
corylus/util/with_attrs.py
corylus/util/yaml_dumper.py
corylus/util/yarra.py
corylus/web/__init__.py
corylus/web/request.py
corylus/xml/__init__.py
corylus/xml/deserialize.py
corylus/xml/parse.py
corylus/xml/serialize.py
corylus-0.3.4.dist-info/METADATA
corylus-0.3.4.dist-info/WHEEL
corylus-0.3.4.dist-info/RECORD
