Metadata-Version: 2.4
Name: corylus
Version: 0.3.4
Summary: utilities
Author-email: Hans Gremmen <hans@leptonix.net>
License: MIT
Requires-Python: >=3.11
Requires-Dist: httpx>=0.28
Requires-Dist: inceptum>=0.8.2
Requires-Dist: python-dateutil>=2
Requires-Dist: pytz>=2025.2
Requires-Dist: pyyaml>=6
Requires-Dist: sqlalchemy>=2
